{
   "experimentId":"179033",
   "sessionId":"2313",
   "conditionID":"001122",
   "debugmode":false,
   "completed":false,
   "finishedConditions":[
      false,
      true,
      true,
      true
   ],
   "currentCondition":3,
   "currentMode":"test",
   "startTime":"2017-08-10T15:31:32.390Z",
   "endTime":"2017-08-10T15:37:50.683Z",
   "expData":{
      "trueValues":[
         [
            1,
            2,
            3,
            4,
            5,
            6,
            7,
            8,
            9,
            10,
            11,
            12,
            13,
            14,
            15,
            16,
            17,
            18,
            19,
            20,
            21,
            22,
            23,
            24,
            25,
            26,
            27,
            28,
            29,
            30,
            31,
            32,
            33,
            34,
            35,
            36,
            37,
            38,
            39,
            40,
            41,
            42,
            43,
            44,
            45,
            46,
            47,
            48,
            49,
            50,
            51,
            52,
            53,
            54,
            55,
            56,
            57,
            58,
            59,
            60,
            61,
            62,
            63,
            64,
            65,
            66,
            67,
            68,
            69,
            70,
            71,
            72,
            73,
            74,
            75,
            76,
            77,
            78,
            79,
            80
         ],
         [
            -0.9807852804032304,
            -0.9238795325112866,
            -0.8314696123025455,
            -0.7071067811865477,
            -0.5555702330196022,
            -0.3826834323650904,
            -0.19509032201612872,
            -2.4492935982947064E-16,
            0.19509032201612825,
            0.38268343236508995,
            0.5555702330196018,
            0.7071067811865474,
            0.8314696123025452,
            0.9238795325112865,
            0.9807852804032303,
            1,
            0.9807852804032307,
            0.9238795325112867,
            0.8314696123025456,
            0.7071067811865483,
            0.5555702330196023,
            0.3826834323650905,
            0.19509032201612797,
            3.6739403974420594E-16,
            -0.19509032201612725,
            -0.38268343236508984,
            -0.5555702330196017,
            -0.7071067811865479,
            -0.8314696123025451,
            -0.9238795325112864,
            -0.9807852804032305,
            -1,
            -0.9807852804032307,
            -0.9238795325112867,
            -0.8314696123025456,
            -0.7071067811865485,
            -0.5555702330196024,
            -0.3826834323650906,
            -0.19509032201612808,
            -4.898587196589413E-16,
            0.19509032201612714,
            0.3826834323650897,
            0.5555702330196016,
            0.7071067811865478,
            0.831469612302545,
            0.9238795325112864,
            0.9807852804032304,
            1,
            0.9807852804032307,
            0.9238795325112868,
            0.8314696123025457,
            0.7071067811865486,
            0.5555702330196025,
            0.3826834323650907,
            0.19509032201612822,
            6.123233995736766E-16,
            -0.195090322016127,
            -0.38268343236508795,
            -0.555570233019603,
            -0.7071067811865477,
            -0.831469612302545,
            -0.9238795325112863,
            -0.9807852804032301,
            -1,
            -0.9807852804032303,
            -0.9238795325112868,
            -0.8314696123025458,
            -0.7071067811865487,
            -0.5555702330196041,
            -0.3826834323650892,
            -0.19509032201612833,
            -7.347880794884119E-16,
            0.1950903220161269,
            0.38268343236508784,
            0.5555702330196028,
            0.7071067811865477,
            0.8314696123025449,
            0.9238795325112863,
            0.9807852804032301,
            1
         ]
      ],
      "chosenPoints":[
         65,
         89,
         96,
         96,
         98,
         100,
         106,
         112,
         113,
         113,
         113,
         113,
         113,
         113,
         113,
         113,
         113,
         114,
         120,
         121,
         121,
         121,
         121,
         121,
         123,
         130,
         130,
         130,
         130,
         130,
         130,
         130,
         140,
         141,
         141,
         144,
         148,
         152,
         152,
         153,
         154,
         154,
         157,
         157,
         157,
         157,
         157,
         158,
         158,
         158,
         158,
         158,
         158,
         158,
         159,
         159,
         159,
         161,
         161,
         162,
         162,
         162,
         162,
         165,
         180,
         180,
         186,
         186,
         186,
         190,
         192,
         193,
         195,
         193,
         193,
         193,
         193,
         194,
         212,
         212,
         212,
         212,
         213,
         212,
         214,
         215,
         215,
         221,
         221,
         224,
         224,
         226,
         231,
         232,
         233,
         234,
         234,
         234,
         238,
         239,
         239,
         239,
         243,
         248,
         250,
         256,
         262,
         262,
         264,
         264,
         264,
         264,
         264,
         264,
         264,
         264,
         291,
         284,
         287,
         287,
         286,
         286,
         286,
         286,
         286,
         287,
         287,
         287,
         287,
         287,
         287,
         288,
         288,
         288,
         288,
         288,
         288,
         288,
         288,
         288,
         288,
         288,
         288,
         288,
         288,
         290,
         306,
         304,
         304,
         308,
         311,
         312,
         184,
         222,
         221,
         226,
         226,
         226,
         226,
         227,
         227,
         227,
         228,
         229,
         229,
         229,
         229,
         229,
         229,
         229,
         229,
         229,
         230,
         230,
         230,
         230,
         230,
         230,
         230,
         230,
         230,
         230,
         230,
         230,
         230,
         230,
         230,
         230,
         230,
         230,
         230,
         230,
         230,
         230,
         230,
         230,
         230,
         230,
         230,
         230,
         230,
         230,
         230,
         223,
         221,
         221,
         221,
         221,
         221,
         221,
         221,
         221,
         220,
         220,
         220,
         220,
         220,
         220,
         220,
         220,
         220,
         220,
         220,
         221,
         222,
         223,
         223,
         223,
         223,
         222,
         223,
         223,
         224,
         224,
         224,
         224,
         224,
         224,
         224,
         224,
         224,
         224,
         224,
         225,
         226,
         226,
         226,
         226,
         226,
         227,
         227,
         227,
         227,
         227,
         227,
         227,
         551.5,
         554.5,
         505.5,
         506.5,
         494.5,
         492.5,
         490.5,
         490.5,
         490.5,
         490.5,
         488.5,
         492.5,
         493.5,
         491.5,
         486.5,
         487.5,
         484.5,
         489.5,
         488.5,
         488.5,
         486.5,
         482.5,
         480.5,
         479.5,
         478.5,
         481.5,
         483.5,
         483.5,
         482.5,
         482.5,
         478.5,
         475.5,
         477.5,
         474.5,
         475.5,
         478.5,
         479.5,
         480.5,
         480.5,
         479.5,
         477.5,
         476.5,
         476.5,
         476.5,
         475.5,
         475.5,
         475.5,
         474.5,
         474.5,
         472.5,
         471.5,
         460.5,
         464.5,
         462.5,
         462.5,
         462.5,
         461.5,
         461.5,
         461.5,
         461.5,
         461.5,
         461.5,
         460.5,
         461.5,
         460.5,
         460.5,
         461.5,
         460.5,
         456.5,
         456.5,
         453.5,
         453.5,
         452.5,
         452.5,
         452.5,
         451.5,
         446.5,
         445.5,
         446.5,
         447.5,
         447.5,
         446.5,
         447.5,
         447.5,
         446.5,
         445.5,
         444.5,
         443.5,
         452.5,
         445.5,
         444.5,
         443.5,
         443.5,
         441.5,
         440.5,
         439.5,
         439.5,
         438.5,
         434.5,
         433.5,
         435.5,
         436.5,
         437.5,
         437.5,
         437.5,
         437.5,
         437.5,
         436.5,
         436.5,
         435.5,
         432.5,
         430.5,
         430.5,
         429.5,
         428.5,
         428.5,
         428.5,
         428.5,
         428.5,
         427.5,
         425.5,
         424.5,
         422.5,
         419.5,
         419.5,
         419.5,
         419.5,
         418.5,
         418.5,
         419.5,
         418.5,
         418.5,
         418.5,
         416.5,
         413.5,
         401.5,
         400.5,
         398.5,
         393.5,
         394.5,
         394.5,
         394.5,
         396.5,
         395.5,
         397.5,
         396.5,
         397.5,
         397.5,
         396.5,
         402.5,
         402.5,
         391.5,
         390.5,
         389.5,
         388.5,
         383.5,
         384.5,
         385.5,
         385.5,
         381.5,
         370.5,
         383.5,
         383.5,
         383.5,
         383.5,
         383.5,
         383.5,
         383.5,
         395.5,
         384.5,
         386.5,
         376.5,
         378.5,
         380.5,
         385.5,
         385.5,
         393.5,
         392.5,
         390.5,
         393.5,
         394.5,
         392.5,
         392.5,
         386.5,
         380.5,
         383.5,
         383.5,
         378.5,
         391.5,
         391.5,
         507.5,
         503.5,
         500.5,
         495.5,
         492.5,
         469.5,
         473.5,
         469.5,
         463.5,
         458.5,
         454.5,
         427.5,
         424.5,
         407.5,
         384.5,
         382.5,
         374.5,
         349.5,
         322.5,
         302.5,
         292.5,
         280.5,
         263.5,
         242.5,
         238.5,
         237.5,
         237.5,
         236.5,
         236.5,
         236.5,
         235.5,
         235.5,
         235.5,
         235.5,
         234.5,
         236.5,
         236.5,
         215.5,
         185.5,
         187.5,
         166.5,
         149.5,
         150.5,
         149.5,
         144.5,
         142.5,
         113.5,
         121.5,
         121.5,
         121.5,
         121.5,
         113.5,
         111.5,
         97.5,
         94.5,
         94.5,
         91.5,
         89.5,
         88.5,
         93.5,
         102.5,
         101.5,
         107.5,
         107.5,
         114.5,
         119.5,
         130.5,
         146.5,
         151.5,
         171.5,
         181.5,
         170.5,
         179.5,
         183.5,
         188.5,
         195.5,
         218.5,
         235.5,
         234.5,
         277.5,
         276.5,
         297.5,
         301.5,
         309.5,
         317.5,
         333.5,
         370.5,
         389.5,
         397.5,
         405.5,
         427.5,
         422.5,
         457.5,
         462.5,
         462.5,
         476.5,
         503.5,
         519.5,
         518.5,
         472.5,
         459.5,
         443.5,
         418.5,
         388.5,
         363.5,
         328.5,
         248.5,
         216.5,
         250.5,
         262.5,
         279.5,
         267.5,
         246.5,
         220.5,
         180.5,
         146.5,
         120.5,
         87.5,
         70.5,
         64.5,
         66.5,
         76.5,
         87.5,
         106.5,
         124.5,
         151.5,
         167.5,
         185.5,
         226.5,
         251.5,
         254.5,
         256.5,
         260.5,
         275.5,
         278.5,
         280.5,
         280.5,
         281.5,
         282.5,
         288.5,
         289.5,
         289.5,
         293.5,
         295.5,
         300.5,
         301.5,
         304.5,
         313.5,
         325.5,
         346.5,
         346.5,
         364.5,
         392.5,
         388.5,
         396.5,
         412.5,
         420.5,
         429.5,
         430.5,
         434.5,
         448.5,
         449.5,
         451.5,
         454.5,
         458.5,
         459.5,
         463.5,
         470.5,
         474.5,
         478.5
      ],
      "submittedPoints":[
         89,
         96,
         100,
         113,
         113,
         121,
         121,
         130,
         130,
         141,
         144,
         154,
         158,
         158,
         158,
         159,
         161,
         162,
         162,
         180,
         186,
         195,
         193,
         212,
         215,
         221,
         224,
         233,
         234,
         239,
         243,
         256,
         262,
         264,
         291,
         286,
         287,
         288,
         288,
         304,
         184,
         221,
         226,
         227,
         229,
         229,
         230,
         230,
         230,
         230,
         230,
         230,
         230,
         230,
         230,
         230,
         230,
         230,
         230,
         230,
         221,
         221,
         221,
         220,
         220,
         220,
         220,
         221,
         223,
         223,
         222,
         223,
         224,
         224,
         225,
         226,
         226,
         227,
         227,
         227,
         505.5,
         492.5,
         492.5,
         491.5,
         484.5,
         486.5,
         482.5,
         480.5,
         479.5,
         481.5,
         482.5,
         478.5,
         475.5,
         475.5,
         480.5,
         476.5,
         475.5,
         474.5,
         472.5,
         460.5,
         462.5,
         461.5,
         456.5,
         446.5,
         445.5,
         452.5,
         444.5,
         443.5,
         441.5,
         439.5,
         436.5,
         436.5,
         428.5,
         428.5,
         425.5,
         424.5,
         422.5,
         419.5,
         418.5,
         418.5,
         413.5,
         401.5,
         400.5,
         398.5,
         394.5,
         394.5,
         395.5,
         396.5,
         397.5,
         397.5,
         396.5,
         402.5,
         390.5,
         388.5,
         383.5,
         384.5,
         385.5,
         383.5,
         383.5,
         395.5,
         384.5,
         386.5,
         376.5,
         378.5,
         380.5,
         385.5,
         385.5,
         393.5,
         392.5,
         390.5,
         393.5,
         394.5,
         392.5,
         392.5,
         386.5,
         380.5,
         383.5,
         378.5,
         391.5,
         391.5,
         507.5,
         503.5,
         473.5,
         463.5,
         424.5,
         382.5,
         349.5,
         322.5,
         242.5,
         234.5,
         185.5,
         149.5,
         144.5,
         121.5,
         89.5,
         93.5,
         101.5,
         114.5,
         119.5,
         151.5,
         183.5,
         218.5,
         234.5,
         276.5,
         317.5,
         370.5,
         405.5,
         457.5,
         462.5,
         476.5,
         503.5,
         519.5,
         518.5,
         472.5,
         459.5,
         443.5,
         418.5,
         388.5,
         363.5,
         279.5,
         267.5,
         220.5,
         180.5,
         146.5,
         120.5,
         87.5,
         70.5,
         66.5,
         76.5,
         87.5,
         106.5,
         124.5,
         151.5,
         185.5,
         226.5,
         254.5,
         260.5,
         280.5,
         280.5,
         282.5,
         288.5,
         289.5,
         295.5,
         301.5,
         313.5,
         325.5,
         346.5,
         364.5,
         388.5,
         396.5,
         412.5,
         420.5,
         430.5,
         434.5,
         449.5,
         454.5,
         463.5,
         470.5,
         474.5,
         478.5
      ]
   },
   "surveyResp":[

   ]
}
